{"config":{"output_file":null,"full_docs":false,"pub_only":false,"reachable_only":false,"distro_crate":false,"signatures":false,"borrow_data":false},"version":"0.19.1","compilation":{"directory":"/home/paruparo/prjs/rust/becomingrustacean/ch14-2-1","program":"/home/paruparo/.rustup/toolchains/nightly-x86_64-unknown-linux-gnu/bin/rls","arguments":[],"output":"/home/paruparo/prjs/rust/becomingrustacean/ch14-2-1/target/rls/debug/deps/libch14_2_1-3ecd77751200f830.rmeta"},"prelude":{"crate_id":{"name":"ch14_2_1","disambiguator":[6101071322338500398,15993307279052902260]},"crate_root":"src","external_crates":[{"file_name":"/home/paruparo/prjs/rust/becomingrustacean/ch14-2-1/src/lib.rs","num":1,"id":{"name":"std","disambiguator":[4915409874566768548,5544031823427913924]}},{"file_name":"/home/paruparo/prjs/rust/becomingrustacean/ch14-2-1/src/lib.rs","num":2,"id":{"name":"core","disambiguator":[17044353007700780372,2918200604221815240]}},{"file_name":"/home/paruparo/prjs/rust/becomingrustacean/ch14-2-1/src/lib.rs","num":3,"id":{"name":"compiler_builtins","disambiguator":[16995631938685242986,13284955835338281890]}},{"file_name":"/home/paruparo/prjs/rust/becomingrustacean/ch14-2-1/src/lib.rs","num":4,"id":{"name":"rustc_std_workspace_core","disambiguator":[14897589902885170584,12420159477491062790]}},{"file_name":"/home/paruparo/prjs/rust/becomingrustacean/ch14-2-1/src/lib.rs","num":5,"id":{"name":"alloc","disambiguator":[8691479991386728181,639557275223572383]}},{"file_name":"/home/paruparo/prjs/rust/becomingrustacean/ch14-2-1/src/lib.rs","num":6,"id":{"name":"libc","disambiguator":[5352780060018682353,5212160423076132458]}},{"file_name":"/home/paruparo/prjs/rust/becomingrustacean/ch14-2-1/src/lib.rs","num":7,"id":{"name":"unwind","disambiguator":[3743531131602818808,2799605859842218829]}},{"file_name":"/home/paruparo/prjs/rust/becomingrustacean/ch14-2-1/src/lib.rs","num":8,"id":{"name":"cfg_if","disambiguator":[17573552924859437949,2252521965207833204]}},{"file_name":"/home/paruparo/prjs/rust/becomingrustacean/ch14-2-1/src/lib.rs","num":9,"id":{"name":"hashbrown","disambiguator":[9226739209782065791,110950369085096429]}},{"file_name":"/home/paruparo/prjs/rust/becomingrustacean/ch14-2-1/src/lib.rs","num":10,"id":{"name":"rustc_std_workspace_alloc","disambiguator":[14107943653937932133,8904570665050324983]}},{"file_name":"/home/paruparo/prjs/rust/becomingrustacean/ch14-2-1/src/lib.rs","num":11,"id":{"name":"rustc_demangle","disambiguator":[5035719718986925764,4655196687560406766]}},{"file_name":"/home/paruparo/prjs/rust/becomingrustacean/ch14-2-1/src/lib.rs","num":12,"id":{"name":"std_detect","disambiguator":[16090878516215906009,6999015639023910513]}},{"file_name":"/home/paruparo/prjs/rust/becomingrustacean/ch14-2-1/src/lib.rs","num":13,"id":{"name":"addr2line","disambiguator":[5155278274645934044,6631537061407573702]}},{"file_name":"/home/paruparo/prjs/rust/becomingrustacean/ch14-2-1/src/lib.rs","num":14,"id":{"name":"gimli","disambiguator":[7524677393090718299,7748664168879547944]}},{"file_name":"/home/paruparo/prjs/rust/becomingrustacean/ch14-2-1/src/lib.rs","num":15,"id":{"name":"object","disambiguator":[679482580766331457,3214831485903047024]}},{"file_name":"/home/paruparo/prjs/rust/becomingrustacean/ch14-2-1/src/lib.rs","num":16,"id":{"name":"miniz_oxide","disambiguator":[16951231520056437187,8607260194695385587]}},{"file_name":"/home/paruparo/prjs/rust/becomingrustacean/ch14-2-1/src/lib.rs","num":17,"id":{"name":"adler","disambiguator":[8430712970266097164,8642054674950797975]}},{"file_name":"/home/paruparo/prjs/rust/becomingrustacean/ch14-2-1/src/lib.rs","num":18,"id":{"name":"panic_unwind","disambiguator":[18152428113670539912,13890257305928077181]}},{"file_name":"/home/paruparo/prjs/rust/becomingrustacean/ch14-2-1/src/lib.rs","num":19,"id":{"name":"test","disambiguator":[14498904035853682465,6389901023909282621]}},{"file_name":"/home/paruparo/prjs/rust/becomingrustacean/ch14-2-1/src/lib.rs","num":20,"id":{"name":"getopts","disambiguator":[7892351477931277615,17554454385566758401]}},{"file_name":"/home/paruparo/prjs/rust/becomingrustacean/ch14-2-1/src/lib.rs","num":21,"id":{"name":"rustc_std_workspace_std","disambiguator":[14554127406014850999,6532013692020139472]}},{"file_name":"/home/paruparo/prjs/rust/becomingrustacean/ch14-2-1/src/lib.rs","num":22,"id":{"name":"unicode_width","disambiguator":[9262527664467592773,1247385687663597828]}},{"file_name":"/home/paruparo/prjs/rust/becomingrustacean/ch14-2-1/src/lib.rs","num":23,"id":{"name":"term","disambiguator":[13543479547215949356,12061631677884588925]}}],"span":{"file_name":"src/lib.rs","byte_start":0,"byte_end":616,"line_start":1,"line_end":32,"column_start":1,"column_end":2}},"imports":[{"kind":"GlobUse","ref_id":null,"span":{"file_name":"src/lib.rs","byte_start":365,"byte_end":366,"line_start":22,"line_end":22,"column_start":21,"column_end":22},"alias_span":null,"name":"*","value":"PrimaryColor, SecondaryColor","parent":{"krate":0,"index":18}}],"defs":[{"kind":"Mod","id":{"krate":0,"index":0},"span":{"file_name":"src/lib.rs","byte_start":0,"byte_end":616,"line_start":1,"line_end":32,"column_start":1,"column_end":2},"name":"","qualname":"::","value":"src/lib.rs","parent":null,"children":[{"krate":0,"index":1},{"krate":0,"index":2},{"krate":0,"index":3},{"krate":0,"index":18},{"krate":0,"index":21}],"decl_id":null,"docs":" # Art","sig":null,"attributes":[{"value":"/ # Art","span":{"file_name":"src/lib.rs","byte_start":0,"byte_end":9,"line_start":1,"line_end":1,"column_start":1,"column_end":10}},{"value":"/","span":{"file_name":"src/lib.rs","byte_start":10,"byte_end":13,"line_start":2,"line_end":2,"column_start":1,"column_end":4}},{"value":"/ A library for modeling artistic concepts.","span":{"file_name":"src/lib.rs","byte_start":14,"byte_end":59,"line_start":3,"line_end":3,"column_start":1,"column_end":46}}]},{"kind":"Mod","id":{"krate":0,"index":3},"span":{"file_name":"src/lib.rs","byte_start":69,"byte_end":74,"line_start":5,"line_end":5,"column_start":9,"column_end":14},"name":"kinds","qualname":"::kinds","value":"src/lib.rs","parent":null,"children":[{"krate":0,"index":4},{"krate":0,"index":11}],"decl_id":null,"docs":"","sig":null,"attributes":[]},{"kind":"TupleVariant","id":{"krate":0,"index":5},"span":{"file_name":"src/lib.rs","byte_start":166,"byte_end":169,"line_start":8,"line_end":8,"column_start":5,"column_end":8},"name":"Red","qualname":"::kinds::PrimaryColor::Red","value":"PrimaryColor::Red","parent":{"krate":0,"index":4},"children":[],"decl_id":null,"docs":"","sig":null,"attributes":[]},{"kind":"TupleVariant","id":{"krate":0,"index":7},"span":{"file_name":"src/lib.rs","byte_start":175,"byte_end":181,"line_start":9,"line_end":9,"column_start":5,"column_end":11},"name":"Yellow","qualname":"::kinds::PrimaryColor::Yellow","value":"PrimaryColor::Yellow","parent":{"krate":0,"index":4},"children":[],"decl_id":null,"docs":"","sig":null,"attributes":[]},{"kind":"TupleVariant","id":{"krate":0,"index":9},"span":{"file_name":"src/lib.rs","byte_start":187,"byte_end":191,"line_start":10,"line_end":10,"column_start":5,"column_end":9},"name":"Blue","qualname":"::kinds::PrimaryColor::Blue","value":"PrimaryColor::Blue","parent":{"krate":0,"index":4},"children":[],"decl_id":null,"docs":"","sig":null,"attributes":[]},{"kind":"Enum","id":{"krate":0,"index":4},"span":{"file_name":"src/lib.rs","byte_start":147,"byte_end":159,"line_start":7,"line_end":7,"column_start":12,"column_end":24},"name":"PrimaryColor","qualname":"::kinds::PrimaryColor","value":"pub enum PrimaryColor { Red, Yellow, Blue, }","parent":null,"children":[{"krate":0,"index":5},{"krate":0,"index":7},{"krate":0,"index":9}],"decl_id":null,"docs":" The primary colors according to the RYB color model.\n","sig":null,"attributes":[{"value":"/ The primary colors according to the RYB color model.","span":{"file_name":"src/lib.rs","byte_start":79,"byte_end":135,"line_start":6,"line_end":6,"column_start":3,"column_end":59}}]},{"kind":"TupleVariant","id":{"krate":0,"index":12},"span":{"file_name":"src/lib.rs","byte_start":291,"byte_end":297,"line_start":15,"line_end":15,"column_start":5,"column_end":11},"name":"Orange","qualname":"::kinds::SecondaryColor::Orange","value":"SecondaryColor::Orange","parent":{"krate":0,"index":11},"children":[],"decl_id":null,"docs":"","sig":null,"attributes":[]},{"kind":"TupleVariant","id":{"krate":0,"index":14},"span":{"file_name":"src/lib.rs","byte_start":303,"byte_end":308,"line_start":16,"line_end":16,"column_start":5,"column_end":10},"name":"Green","qualname":"::kinds::SecondaryColor::Green","value":"SecondaryColor::Green","parent":{"krate":0,"index":11},"children":[],"decl_id":null,"docs":"","sig":null,"attributes":[]},{"kind":"TupleVariant","id":{"krate":0,"index":16},"span":{"file_name":"src/lib.rs","byte_start":314,"byte_end":320,"line_start":17,"line_end":17,"column_start":5,"column_end":11},"name":"Purple","qualname":"::kinds::SecondaryColor::Purple","value":"SecondaryColor::Purple","parent":{"krate":0,"index":11},"children":[],"decl_id":null,"docs":"","sig":null,"attributes":[]},{"kind":"Enum","id":{"krate":0,"index":11},"span":{"file_name":"src/lib.rs","byte_start":270,"byte_end":284,"line_start":14,"line_end":14,"column_start":12,"column_end":26},"name":"SecondaryColor","qualname":"::kinds::SecondaryColor","value":"pub enum SecondaryColor { Orange, Green, Purple, }","parent":null,"children":[{"krate":0,"index":12},{"krate":0,"index":14},{"krate":0,"index":16}],"decl_id":null,"docs":" The secondary colors according to the RYB color model.\n","sig":null,"attributes":[{"value":"/ The secondary colors according to the RYB color model.","span":{"file_name":"src/lib.rs","byte_start":200,"byte_end":258,"line_start":13,"line_end":13,"column_start":3,"column_end":61}}]},{"kind":"Mod","id":{"krate":0,"index":18},"span":{"file_name":"src/lib.rs","byte_start":337,"byte_end":342,"line_start":21,"line_end":21,"column_start":9,"column_end":14},"name":"utils","qualname":"::utils","value":"src/lib.rs","parent":null,"children":[{"krate":0,"index":19},{"krate":0,"index":20}],"decl_id":null,"docs":"","sig":null,"attributes":[]},{"kind":"Local","id":{"krate":0,"index":1073741844},"span":{"file_name":"src/lib.rs","byte_start":468,"byte_end":470,"line_start":26,"line_end":26,"column_start":14,"column_end":16},"name":"c1","qualname":"::utils::mix::c1","value":"kinds::PrimaryColor","parent":null,"children":[],"decl_id":null,"docs":"","sig":null,"attributes":[]},{"kind":"Local","id":{"krate":0,"index":536870932},"span":{"file_name":"src/lib.rs","byte_start":486,"byte_end":488,"line_start":26,"line_end":26,"column_start":32,"column_end":34},"name":"c2","qualname":"::utils::mix::c2","value":"kinds::PrimaryColor","parent":null,"children":[],"decl_id":null,"docs":"","sig":null,"attributes":[]},{"kind":"Function","id":{"krate":0,"index":20},"span":{"file_name":"src/lib.rs","byte_start":464,"byte_end":467,"line_start":26,"line_end":26,"column_start":10,"column_end":13},"name":"mix","qualname":"::utils::mix","value":"pub fn mix(PrimaryColor, PrimaryColor) -> SecondaryColor","parent":null,"children":[],"decl_id":null,"docs":" Combines two primary colors in equal amounts to create\n a secondary color.\n","sig":null,"attributes":[{"value":"/ Combines two primary colors in equal amounts to create","span":{"file_name":"src/lib.rs","byte_start":371,"byte_end":429,"line_start":24,"line_end":24,"column_start":3,"column_end":61}},{"value":"/ a secondary color.","span":{"file_name":"src/lib.rs","byte_start":432,"byte_end":454,"line_start":25,"line_end":25,"column_start":3,"column_end":25}}]}],"impls":[],"refs":[{"kind":"Mod","span":{"file_name":"src/lib.rs","byte_start":351,"byte_end":356,"line_start":22,"line_end":22,"column_start":7,"column_end":12},"ref_id":{"krate":0,"index":3}},{"kind":"Mod","span":{"file_name":"src/lib.rs","byte_start":358,"byte_end":363,"line_start":22,"line_end":22,"column_start":14,"column_end":19},"ref_id":{"krate":0,"index":3}},{"kind":"Type","span":{"file_name":"src/lib.rs","byte_start":472,"byte_end":484,"line_start":26,"line_end":26,"column_start":18,"column_end":30},"ref_id":{"krate":0,"index":4}},{"kind":"Type","span":{"file_name":"src/lib.rs","byte_start":490,"byte_end":502,"line_start":26,"line_end":26,"column_start":36,"column_end":48},"ref_id":{"krate":0,"index":4}},{"kind":"Type","span":{"file_name":"src/lib.rs","byte_start":507,"byte_end":521,"line_start":26,"line_end":26,"column_start":53,"column_end":67},"ref_id":{"krate":0,"index":11}},{"kind":"Type","span":{"file_name":"src/lib.rs","byte_start":584,"byte_end":590,"line_start":29,"line_end":29,"column_start":21,"column_end":27},"ref_id":{"krate":0,"index":12}},{"kind":"Type","span":{"file_name":"src/lib.rs","byte_start":568,"byte_end":582,"line_start":29,"line_end":29,"column_start":5,"column_end":19},"ref_id":{"krate":0,"index":11}}],"macro_refs":[],"relations":[]}